layyer/__init__.py
layyer/discodef/__init__.py
layyer/discodef/cifar10_model.py
layyer/discodef/disco_model.py
layyer/discodef/getData.py
layyer/discodef/mnist_model.py
layyer/discodef/utils.py
layyer-0.0.13.dist-info/LICENSE.txt
layyer-0.0.13.dist-info/METADATA
layyer-0.0.13.dist-info/WHEEL
layyer-0.0.13.dist-info/top_level.txt
layyer-0.0.13.dist-info/RECORD
