Metadata-Version: 2.1
Name: layyer
Version: 0.0.13
Summary: layyer lib
Home-page: UNKNOWN
Author: Pranpaveen Lay.
Author-email: pranpaveen.lay@gmail.com
License: UNKNOWN
Platform: UNKNOWN
Classifier: Programming Language :: Python :: 3
Classifier: License :: OSI Approved :: MIT License
Classifier: Operating System :: OS Independent
Requires-Python: >=3.6
Requires-Dist: numpy
Requires-Dist: advertorch
